{
  "$schema": "https://schemas.wp.org/trunk/block.json",
  "apiVersion": 3,
  "name": "create-block/my-first-block",
  "version": "0.1.0",
  "title": "Offers",
  "category": "widgets",
  "icon": "calendar",
  "description": "Some text.",
  "example": {},
  "supports": {
    "html": false
  },
  "attributes": {
    "endpointUrl": {
      "default": ""
      "type": "string",
    }
  },
  "textdomain": "my-first-block",
  "editorScript": "file:./index.js",
  "editorStyle": [
    "file:./index.css",
    "dashicons"
  ],
  "style": "file:./style-index.css",
  "viewScript": "file:./view.js"
}
